egos_helpers/__init__.py
egos_helpers/constants.py
egos_helpers/core.py
egos_helpers/log.py
egos_helpers/py.typed
egos_helpers-1.2.3.dist-info/METADATA
egos_helpers-1.2.3.dist-info/WHEEL
egos_helpers-1.2.3.dist-info/licenses/LICENSE
egos_helpers-1.2.3.dist-info/RECORD
