Metadata-Version: 2.4
Name: egos-helpers
Version: 1.2.3
Summary: A python library for helper functions
License: MIT License
License-File: LICENSE
Author: Alex Thomae
Author-email: egos-helpers@egos.tech
Requires-Python: >=3.12
Classifier: Intended Audience :: Developers
Classifier: Natural Language :: English
Classifier: Operating System :: OS Independent
Classifier: Programming Language :: Python
Classifier: Programming Language :: Python :: 3
Classifier: Programming Language :: Python :: 3.12
Classifier: Programming Language :: Python :: 3.13
Classifier: Programming Language :: Python :: 3.14
Classifier: Programming Language :: Python :: Implementation :: PyPy
Classifier: Topic :: Software Development :: Libraries
Requires-Dist: pygelf (==0.4.3)
Project-URL: Homepage, https://gitlab.com/egos-tech/egos-helpers
Project-URL: Source, https://gitlab.com/egos-tech/egos-helpers
